[
    {
      "username": "annotator",
      "age": 45,
      "sex": "female",
      "education_level": "Master's",
      "sexual_orientation": "Heterosexual",
      "demographic_group": "Indigenous",
      "current_employment": "Botanist",
      "special_instructions": "",
      "personality_characteristics": [
        "calm",
        "empathetic",
        "insightful",
        "relaxed"
      ]
    },
    {
      "username": "annotator",
      "age": 60,
      "sex": "male",
      "education_level": "PhD",
      "sexual_orientation": "Asexual",
      "demographic_group": "Caucasian",
      "current_employment": "Historian",
      "special_instructions": "",
      "personality_characteristics": [
        "analytical",
        "reserved",
        "meticulous",
        "nostalgic"
      ]
    },
    {
      "username": "annotator",
      "age": 50,
      "sex": "male",
      "education_level": "No formal education",
      "sexual_orientation": "Heterosexual",
      "demographic_group": "Middle Eastern",
      "current_employment": "Farmer",
      "special_instructions": "",
      "personality_characteristics": [
        "hardworking",
        "practical",
        "resilient",
        "content"
      ]
    },
    {
      "username": "annotator",
      "age": 28,
      "sex": "male",
      "education_level": "Bachelor's",
      "sexual_orientation": "Homosexual",
      "demographic_group": "Caucasian",
      "current_employment": "Research Scientist",
      "special_instructions": "",
      "personality_characteristics": [
        "introspective",
        "thoughtful",
        "detail-oriented",
        "melancholic"
      ]
    },
    {
      "username": "annotator",
      "age": 40,
      "sex": "female",
      "education_level": "Some College",
      "sexual_orientation": "Heterosexual",
      "demographic_group": "Pacific Islander",
      "current_employment": "Travel Blogger",
      "special_instructions": "",
      "personality_characteristics": [
        "spontaneous",
        "energetic",
        "fearless",
        "excited"
      ]
    },
    {
      "username": "annotator",
      "age": 65,
      "sex": "male",
      "education_level": "PhD",
      "sexual_orientation": "Heterosexual",
      "demographic_group": "South Asian",
      "current_employment": "Retired Philosopher",
      "special_instructions": "",
      "personality_characteristics": [
        "wise",
        "stoic",
        "pragmatic",
        "serene"
      ]
    },
    {
      "username": "annotator",
      "age": 32,
      "sex": "non-binary",
      "education_level": "Master's",
      "sexual_orientation": "Bisexual",
      "demographic_group": "Black",
      "current_employment": "Cybersecurity Expert",
      "special_instructions": "",
      "personality_characteristics": [
        "rebellious",
        "clever",
        "cynical",
        "frustrated"
      ]
    },
    {
      "username": "annotator",
      "age": 38,
      "sex": "female",
      "education_level": "Bachelor's",
      "sexual_orientation": "Heterosexual",
      "demographic_group": "Latino",
      "current_employment": "Registered Nurse",
      "special_instructions": "",
      "personality_characteristics": [
        "compassionate",
        "patient",
        "diligent",
        "overwhelmed"
      ]
    },
    {
      "username": "annotator",
      "age": 21,
      "sex": "male",
      "education_level": "Some College",
      "sexual_orientation": "Pansexual",
      "demographic_group": "White",
      "current_employment": "Game Developer",
      "special_instructions": "",
      "personality_characteristics": [
        "strategic",
        "meticulous",
        "nerdy",
        "hyper-focused"
      ]
    },
    {
      "username": "annotator",
      "age": 27,
      "sex": "female",
      "education_level": "Master's",
      "sexual_orientation": "Lesbian",
      "demographic_group": "Arab",
      "current_employment": "Poet",
      "special_instructions": "",
      "personality_characteristics": [
        "sensitive",
        "imaginative",
        "quiet",
        "moody"
      ]
    },
    {
      "username": "annotator",
      "age": 55,
      "sex": "male",
      "education_level": "Master's",
      "sexual_orientation": "Heterosexual",
      "demographic_group": "White",
      "current_employment": "Stock Trader",
      "special_instructions": "",
      "personality_characteristics": [
        "calculating",
        "rational",
        "skeptical",
        "tense"
      ]
    }
  ]
  